ocr_translate_paddle/__init__.py
ocr_translate_paddle/plugin.py
ocr_translate_paddle-0.3.1.dist-info/entry_points.txt
ocr_translate_paddle-0.3.1.dist-info/licenses/LICENSE.txt
ocr_translate_paddle-0.3.1.dist-info/WHEEL
ocr_translate_paddle-0.3.1.dist-info/METADATA
ocr_translate_paddle-0.3.1.dist-info/RECORD
