Metadata-Version: 2.4
Name: ocr_translate-paddle
Version: 0.3.1
Summary: Plugins to enable usage of PaddleOCR in ocr_translate
Keywords: django,translation
Requires-Python: >=3.10
Classifier: Programming Language :: Python
Classifier: Programming Language :: Python :: 3.10
Classifier: Programming Language :: Python :: 3.11
Classifier: Programming Language :: Python :: 3.12
Classifier: Programming Language :: Python :: 3.13
License-File: LICENSE.txt
Requires-Dist: django-ocr_translate>=0.7.0,<1.0
Requires-Dist: pandas~=2.3.2
Requires-Dist: protobuf~=6.32.0
Requires-Dist: safetensors~=0.6.2
Requires-Dist: paddleocr~=3.2.0
Requires-Dist: paddlepaddle~=3.2.0
Requires-Dist: paddlex~=3.2.1
Requires-Dist: pre-commit ; extra == "pre-commit"
Requires-Dist: pylint ; extra == "pre-commit"
Requires-Dist: pylint-pytest ; extra == "pre-commit"
Requires-Dist: pylint-django ; extra == "pre-commit"
Requires-Dist: flit ; extra == "release"
Requires-Dist: pytest ; extra == "tests"
Requires-Dist: pytest-cov ; extra == "tests"
Requires-Dist: pytest-django ; extra == "tests"
Requires-Dist: pytest-regressions ; extra == "tests"
Project-URL: Source, https://github.com/Crivella/ocr_translate-paddle
Provides-Extra: pre-commit
Provides-Extra: release
Provides-Extra: tests
